JSONEyeX/__init__.py
JSONEyeX/validator.py
JSONEyeX-0.0.10.dist-info/METADATA
JSONEyeX-0.0.10.dist-info/WHEEL
JSONEyeX-0.0.10.dist-info/top_level.txt
JSONEyeX-0.0.10.dist-info/RECORD
