Metadata-Version: 2.1
Name: JSONEyeX
Version: 0.0.10
Summary: A lightweight and efficient JSON validation tool for Python.
Home-page: https://github.com/venkatasidhartha/JSONEyeX.git
Author: venkata sidhartha (sidhu)
Author-email: venkatasidhartha@gmail.com
License: UNKNOWN
Keywords: python,json,validation,json-validator
Platform: UNKNOWN
Requires-Dist: wheel
